devicer/__init__.py
devicer/cache.py
devicer/get_device.py
devicer/py.typed
devicer-0.1.1.dist-info/WHEEL
devicer-0.1.1.dist-info/METADATA
devicer-0.1.1.dist-info/RECORD
